<?xml version="1.0" encoding="utf-8" ?>
<dwsync>
<file name="BinlogController.php" server="ec2-3-144-86-188.us-east-2.compute.amazonaws.com//var/www/html/" local="133202757120000000" remote="133202757120000000" Dst="2" />
<file name="CollationsController.php" server="ec2-3-144-86-188.us-east-2.compute.amazonaws.com//var/www/html/" local="133202757120000000" remote="133202757120000000" Dst="2" />
<file name="DatabasesController.php" server="ec2-3-144-86-188.us-east-2.compute.amazonaws.com//var/www/html/" local="133202757120000000" remote="133202757120000000" Dst="2" />
<file name="EnginesController.php" server="ec2-3-144-86-188.us-east-2.compute.amazonaws.com//var/www/html/" local="133202757120000000" remote="133202757120000000" Dst="2" />
<file name="ExportController.php" server="ec2-3-144-86-188.us-east-2.compute.amazonaws.com//var/www/html/" local="133202757120000000" remote="133202757120000000" Dst="2" />
<file name="ImportController.php" server="ec2-3-144-86-188.us-east-2.compute.amazonaws.com//var/www/html/" local="133202757120000000" remote="133202757120000000" Dst="2" />
<file name="PluginsController.php" server="ec2-3-144-86-188.us-east-2.compute.amazonaws.com//var/www/html/" local="133202757120000000" remote="133202757120000000" Dst="2" />
<file name="PrivilegesController.php" server="ec2-3-144-86-188.us-east-2.compute.amazonaws.com//var/www/html/" local="133202757120000000" remote="133202757120000000" Dst="2" />
<file name="ReplicationController.php" server="ec2-3-144-86-188.us-east-2.compute.amazonaws.com//var/www/html/" local="133202757120000000" remote="133202757120000000" Dst="2" />
<file name="ShowEngineController.php" server="ec2-3-144-86-188.us-east-2.compute.amazonaws.com//var/www/html/" local="133202757120000000" remote="133202757120000000" Dst="2" />
<file name="SqlController.php" server="ec2-3-144-86-188.us-east-2.compute.amazonaws.com//var/www/html/" local="133202757120000000" remote="133202757120000000" Dst="2" />
<file name="UserGroupsController.php" server="ec2-3-144-86-188.us-east-2.compute.amazonaws.com//var/www/html/" local="133202757120000000" remote="133202757120000000" Dst="2" />
<file name="UserGroupsFormController.php" server="ec2-3-144-86-188.us-east-2.compute.amazonaws.com//var/www/html/" local="133202757120000000" remote="133202757120000000" Dst="2" />
<file name="VariablesController.php" server="ec2-3-144-86-188.us-east-2.compute.amazonaws.com//var/www/html/" local="133202757120000000" remote="133202757120000000" Dst="2" />
</dwsync>