<?xml version="1.0" encoding="utf-8" ?>
<dwsync>
<file name="Console.php" server="ec2-3-144-86-188.us-east-2.compute.amazonaws.com//var/www/html/" local="133202757120000000" remote="133202757120000000" Dst="2" />
<file name="Debug.php" server="ec2-3-144-86-188.us-east-2.compute.amazonaws.com//var/www/html/" local="133202757120000000" remote="133202757120000000" Dst="2" />
<file name="Export.php" server="ec2-3-144-86-188.us-east-2.compute.amazonaws.com//var/www/html/" local="133202757120000000" remote="133202757120000000" Dst="2" />
<file name="Import.php" server="ec2-3-144-86-188.us-east-2.compute.amazonaws.com//var/www/html/" local="133202757120000000" remote="133202757120000000" Dst="2" />
<file name="Schema.php" server="ec2-3-144-86-188.us-east-2.compute.amazonaws.com//var/www/html/" local="133202757120000000" remote="133202757120000000" Dst="2" />
<file name="Server.php" server="ec2-3-144-86-188.us-east-2.compute.amazonaws.com//var/www/html/" local="133202757120000000" remote="133202757120000000" Dst="2" />
<file name="SqlQueryBox.php" server="ec2-3-144-86-188.us-east-2.compute.amazonaws.com//var/www/html/" local="133202757120000000" remote="133202757120000000" Dst="2" />
<file name="Transformations.php" server="ec2-3-144-86-188.us-east-2.compute.amazonaws.com//var/www/html/" local="133202757120000000" remote="133202757120000000" Dst="2" />
</dwsync>